TISApi/BytesHelper.py
TISApi/DiscoveryHelpers.py
TISApi/__init__.py
TISApi/api.py
TISApi/crc.py
TISApi/shared.py
TISApi/utils.py
TISApi/Protocols/__init__.py
TISApi/Protocols/udp/AckCoordinator.py
TISApi/Protocols/udp/PacketDispatcher.py
TISApi/Protocols/udp/PacketExtractor.py
TISApi/Protocols/udp/PacketProtocol.py
TISApi/Protocols/udp/PacketReceiver.py
TISApi/Protocols/udp/PacketSender.py
TISApi/Protocols/udp/ProtocolHandler.py
TISApi/Protocols/udp/__init__.py
TISApi/Protocols/udp/PacketHandlers/ControlResponseHandler.py
TISApi/Protocols/udp/PacketHandlers/DiscoveryFeedbackHandler.py
TISApi/Protocols/udp/PacketHandlers/UpdateResponseHandler.py
TISApi/Protocols/udp/PacketHandlers/__init__.py
TISApi/components/switch/base_switch.py
tisapi-0.1.15.dist-info/METADATA
tisapi-0.1.15.dist-info/WHEEL
tisapi-0.1.15.dist-info/licenses/LICENSE
tisapi-0.1.15.dist-info/RECORD
