Metadata-Version: 2.4
Name: TISApi
Version: 0.1.15
Summary: A library for TIS Control
Project-URL: Homepage, https://github.com/KarimTIS
Project-URL: Issues, https://github.com/KarimTIS/issues
Author-email: Karim Bahgat <karim@tiscontrol.com>, Ibrahim Mohamed <ibrali2001.ia@gmail.com>
License-File: LICENSE
Classifier: License :: OSI Approved :: MIT License
Classifier: Operating System :: POSIX :: Linux
Classifier: Programming Language :: Python :: 3
Requires-Python: >=3.11
